{
    "Anti-Debugging": {
        "DebugSub": 0,
        "Native Code Debugger": {
            "Using Timing Check": 0,
            "Using Signals": 8,
            "Using TracerPID": 1,
            "Preempt Ptrace API": 0,
            "Anti Dump": 0
        },
        "JDWP Debugger": {
            "Debugger Related Value": 120,
            "Debugger Related Value OLD": 117,
            "Breakpointset Structure": 0,
            "Altering Debugger Memory": 0
        }
    },
    "Anti Virtual Environment": {
        "EnvironmentSub": 0,
        "Anti-Emulator": {
            "Sum": 130,
            "Static": {
                "Device Identifier": 125,
                "Device Identifier OLD": 2,
                "Current Build": 130,
                "Current Build OLD": 121,
                "Telephony Manager": 0,
                "Hardware Components": 6,
                "Emulator Related Strings and System Properties": 82,
                "Emulator Related Strings and System Properties OLD": 80
            },
            "Dynamic": {
                "Sensor Information": 39,
                "CPU Performance": {
                    "Context Switch Based Detection": 0,
                    "Translation Block Cache Based Detection": 0,
                    "Misaligned Vectorization Based Detection": 1,
                    "Updates to Execution State Bits": 0
                }
            }
        },
        "Anti App-Level Virtualization": {
            "Sum": 1,
            "File Path": 1,
            "Share UID": 0,
            "Port Detection": 0,
            "Code Injection And Hooking": 0
        }
    },
    "Anti-Tampering": {
        "TamperSub": 0,
        "SafetyNet Attestation": 15,
        "SafetyNet Attestation OLD": 15,
        "Installer Verification": 133,
        "Installer Verification OLD": 125,
        "Code Integrity Checking": 110,
        "Code Integrity Checking OLD": 91,
        "Signature Checking": 135,
        "Signature Checking OLD": 132
    },
    "Anti-Hooking": {
        "HookSub": 0,
        "Xposed": 8,
        "Xposed OLD": 8,
        "Frida": 0,
        "Frida OLD": 0
    },
    "Root Detection": {
        "RootSub": 0,
        "Check Installed Packages": 105,
        "Check Shell Commands Execution": 116,
        "Check Build Tag and System Properties": 127,
        "Directory Permissions": 13
    },
    "Sum": {
        "Sub": 0,
        "Major": 0,
        "Sub_0": 0,
        "Sub_1": 0,
        "Sub_2": 4,
        "Sub_3": 1,
        "Sub_4": 2,
        "Sub_5": 2,
        "Sub_6": 5,
        "Sub_7": 6,
        "Sub_8": 13,
        "Sub_9": 21,
        "Sub_10": 41,
        "Sub_11": 22,
        "Sub_12": 9,
        "Sub_13": 5,
        "Sub_14": 4,
        "Sub_15": 0,
        "Sub_16": 0,
        "Sub_17": 0,
        "Sub_18": 0,
        "Sub_19": 0,
        "Sub_20": 0,
        "Sub_21": 0,
        "Sub_22": 0,
        "Sub_23": 0,
        "Sub_24": 0,
        "Sub_25": 0,
        "Sub_26": 0,
        "Sub_27": 0,
        "Sub_28": 0,
        "Sub_29": 0,
        "Sub_30": 0,
        "Sub_31": 0,
        "Sub_32": 0,
        "Sub_33": 0,
        "Sub_34": 0,
        "Major_0": 0,
        "Major_1": 4,
        "Major_2": 3,
        "Major_3": 9,
        "Major_4": 111,
        "Major_5": 8
    },
    "Test": {
        "Using Timing Check": {
            "B1": 0,
            "B2": 0,
            "B3": 0
        },
        "shareUID": {
            "A": 6,
            "B": 0,
            "C": 24,
            "D": 133,
            "E": 134,
            "F": 135
        },
        "HardwareComponents": {
            "A": 5,
            "B": 0,
            "C": 0,
            "D": 0,
            "E": 0,
            "F": 0,
            "G": 0,
            "H": 0,
            "I": 0,
            "J": 0,
            "K": 8,
            "L": 18,
            "KL": 1
        },
        "EmulatorRelated": {
            "A": 130,
            "B": 50,
            "C": 124,
            "D": 8,
            "E": 42,
            "F": 50,
            "G": 121,
            "H": 8,
            "ABC": 50,
            "DE": 47,
            "FGH": 50
        },
        "Presence": {
            "A": 0,
            "B": 0,
            "C": 0,
            "D": 0,
            "E": 0,
            "F": 0,
            "AB": 0,
            "DE": 0,
            "EFC": 0
        },
        "Debugger": {
            "A": 12,
            "B": 130,
            "C": 0,
            "D": 12,
            "E": 117,
            "F": 0,
            "G": 0,
            "H": 4,
            "I": 11,
            "J": 12,
            "K": 1,
            "L": 0,
            "M": 0,
            "N": 0,
            "O": 0,
            "P": 0,
            "Q": 0,
            "R": 0,
            "S": 0,
            "AB": 12,
            "NO": 0,
            "PQ": 0,
            "RS": 0
        },
        "DUMP": {
            "A": 0,
            "B": 6,
            "C": 34,
            "D": 0
        },
        "HashValueComparison": {
            "A": 0,
            "B": 0
        },
        "AlteringDebuggerMemory": {
            "A": 0,
            "B": 0
        },
        "ContextSwitchBasedDetection": {
            "A": 45,
            "B": 45,
            "C": 33
        },
        "CheckShellCommandsExecution": {
            "A": 0,
            "B": 0,
            "C": 110
        },
        "CheckBuildTagandSystemProperties": {
            "A": 127,
            "B": 0,
            "C": 0,
            "D": 0,
            "E": 1,
            "F": 130,
            "G": 12,
            "EFG": 12
        },
        "DirectoryPermissions": {
            "A": 13,
            "B": 134
        }
    }
}